codem/__init__.py
codem/__main__.py
codem/main.py
codem/lib/__init__.py
codem/lib/console.py
codem/lib/log.py
codem/lib/progress.py
codem/lib/resources.py
codem/preprocessing/__init__.py
codem/preprocessing/preprocess.py
codem/registration/__init__.py
codem/registration/apply.py
codem/registration/dsm.py
codem/registration/icp.py
codem-0.26.2.dist-info/licenses/LICENSE
vcd/__init__.py
vcd/__main__.py
vcd/main.py
vcd/meshing/__init__.py
vcd/meshing/mesh.py
vcd/preprocessing/__init__.py
vcd/preprocessing/preprocess.py
codem-0.26.2.dist-info/METADATA
codem-0.26.2.dist-info/WHEEL
codem-0.26.2.dist-info/entry_points.txt
codem-0.26.2.dist-info/top_level.txt
codem-0.26.2.dist-info/RECORD
