Metadata-Version: 2.4
Name: codem
Version: 0.26.2
Summary: A package for co-registering geospatial data
Author: Jesse Shanahan, Bahirah Adewunmi
Author-email: Preston Hartzell <pjhartzell@uh.edu>
Maintainer-email: Ognyan Moore <ogi@hobu.co>
License: Apache-2.0
Project-URL: homepage, https://github.com/NCALM-UH/CODEM
Project-URL: repository, https://github.com/NCALM-UH/CODEM
Classifier: Development Status :: 4 - Beta
Classifier: Intended Audience :: Information Technology
Classifier: Intended Audience :: Science/Research
Classifier: License :: OSI Approved :: Apache Software License
Classifier: Topic :: Scientific/Engineering :: GIS
Classifier: Topic :: Scientific/Engineering :: Image Processing
Requires-Python: >=3.9
License-File: LICENSE
Requires-Dist: typing-extensions
Dynamic: license-file
